gather_leads/__init__.py
gather_leads/_version.py
gather_leads/cli.py
gather_leads/constants.py
gather_leads/gsearch.py
gather_leads/main.py
gather_leads/models.py
gather_leads/transform.py
gather_leads-0.1.0.dist-info/licenses/LICENSE
gather_leads-0.1.0.dist-info/METADATA
gather_leads-0.1.0.dist-info/WHEEL
gather_leads-0.1.0.dist-info/entry_points.txt
gather_leads-0.1.0.dist-info/top_level.txt
gather_leads-0.1.0.dist-info/RECORD
