Metadata-Version: 2.4
Name: gather-leads
Version: 0.1.0
Summary: Utility to create an Excel file from a text query to Google Places
License-Expression: MIT
Project-URL: Repository, https://github.com/papanikos/gather-leads.git
Requires-Python: >=3.11
License-File: LICENSE
Requires-Dist: openpyxl>=3.1.5
Requires-Dist: pandas>=2.2.3
Requires-Dist: requests>=2.32.3
Dynamic: license-file
